dapc/__init__.py
dapc/dapc_main.py
dapc-3.5.2.dist-info/METADATA
dapc-3.5.2.dist-info/WHEEL
dapc-3.5.2.dist-info/top_level.txt
dapc-3.5.2.dist-info/RECORD
