Metadata-Version: 2.1
Name: dapc
Version: 3.5.2
Summary: DAPC is a simple audio process python library. This is the first version of Python extension library for dapc.
Author: Duyu09
Author-email: qluduyu09@163.com
Requires-Dist: numpy
Requires-Dist: scipy
